{
    "145122063173156864": {
        "display_name": "Reminissions",
        "logs": [
            {
                "timestamp": "[2025-03-09 21:38:17]",
                "action": "Added",
                "amount": 10000,
                "description": "boss participation"
            }
        ]
    },
    "316168392275001358": {
        "display_name": "Bazookahands",
        "logs": [
            {
                "timestamp": "[2025-03-09 21:38:33]",
                "action": "Added",
                "amount": 10000,
                "description": "boss participation"
            },
            {
                "timestamp": "[2025-03-12 18:56:37]",
                "action": "Removed",
                "amount": 1,
                "description": "test"
            },
            {
                "timestamp": "[2025-03-12 18:57:20]",
                "action": "Added",
                "amount": 1,
                "description": "test"
            }
        ]
    },
    "686229371224326145": {
        "display_name": "Indingo",
        "logs": [
            {
                "timestamp": "[2025-03-09 21:38:33]",
                "action": "Added",
                "amount": 10000,
                "description": "boss participation"
            }
        ]
    },
    "576508116871675954": {
        "display_name": "Retka28",
        "logs": [
            {
                "timestamp": "[2025-03-09 21:38:33]",
                "action": "Added",
                "amount": 10000,
                "description": "boss participation"
            }
        ]
    }
}